{
  "completed_seasons": [
    "2007",
    "2008",
    "2009",
    "2010",
    "2011",
    "2012",
    "2013",
    "2014",
    "2015",
    "2016",
    "2017",
    "2018",
    "2019",
    "2020",
    "2021",
    "2022",
    "2023",
    "2024",
    "2025"
  ],
  "last_update": "2026-02-01T04:41:55.591077",
  "current_season_last_update": "2026-02-01T04:20:00.610936",
  "last_game_log_date": "2026-02-01",
  "last_injury_update": "2026-02-02T01:22:47.746356",
  "last_team_stats_update": "2026-02-02T01:22:48.896068"
}